votion/__init__.py
votion/foo.py
votion/main.py
votion/tests/__init__.py
votion/tests/test_foo.py
votion-0.0.5.dist-info/entry_points.txt
votion-0.0.5.dist-info/LICENSE
votion-0.0.5.dist-info/WHEEL
votion-0.0.5.dist-info/METADATA
votion-0.0.5.dist-info/RECORD
