Metadata-Version: 2.1
Name: votion
Version: 0.0.5
Summary: Docker image build tool
Home-page: https://github.com/weastur/votion
License: MIT
Author: Pavel Sapezhko
Author-email: me@weastur.com
Maintainer: Pavel Sapezhko
Maintainer-email: me@weastur.com
Requires-Python: >=3.6,<4.0
Classifier: License :: OSI Approved :: MIT License
Classifier: Programming Language :: Python :: 3
Classifier: Programming Language :: Python :: 3.6
Classifier: Programming Language :: Python :: 3.7
Classifier: Programming Language :: Python :: 3.8
Classifier: Programming Language :: Python :: 3.9
Requires-Dist: docker (>=4.2.0,<5.0.0)
Project-URL: Repository, https://github.com/weastur/votion
